reargumentparse/__init__.py
reargumentparse/reinit.py
reargumentparse-0.0.2.dist-info/LICENSE
reargumentparse-0.0.2.dist-info/METADATA
reargumentparse-0.0.2.dist-info/WHEEL
reargumentparse-0.0.2.dist-info/top_level.txt
reargumentparse-0.0.2.dist-info/RECORD
