Metadata-Version: 2.1
Name: reargumentparse
Version: 0.0.2
Summary: python package to handly python configurations
Home-page: https://github.com/packages/packages
Author: joinerenc
Author-email: pymodify231@gmail.com
Classifier: Programming Language :: Python :: 3
Classifier: License :: OSI Approved :: MIT License
Classifier: Operating System :: OS Independent
Requires-Python: >=3.7
License-File: LICENSE
